odoo9_addon_purchase_request_to_rfq_order_approved-9.0.1.0.0.99.dev5-py2.7-nspkg.pth
odoo9_addon_purchase_request_to_rfq_order_approved-9.0.1.0.0.99.dev5.dist-info/METADATA
odoo9_addon_purchase_request_to_rfq_order_approved-9.0.1.0.0.99.dev5.dist-info/RECORD
odoo9_addon_purchase_request_to_rfq_order_approved-9.0.1.0.0.99.dev5.dist-info/WHEEL
odoo9_addon_purchase_request_to_rfq_order_approved-9.0.1.0.0.99.dev5.dist-info/namespace_packages.txt
odoo9_addon_purchase_request_to_rfq_order_approved-9.0.1.0.0.99.dev5.dist-info/top_level.txt
odoo_addons/purchase_request_to_rfq_order_approved/README.rst
odoo_addons/purchase_request_to_rfq_order_approved/__init__.py
odoo_addons/purchase_request_to_rfq_order_approved/__openerp__.py
odoo_addons/purchase_request_to_rfq_order_approved/init_hook.py
odoo_addons/purchase_request_to_rfq_order_approved/i18n/es.po
odoo_addons/purchase_request_to_rfq_order_approved/i18n/fr.po
odoo_addons/purchase_request_to_rfq_order_approved/i18n/sl.po
odoo_addons/purchase_request_to_rfq_order_approved/models/__init__.py
odoo_addons/purchase_request_to_rfq_order_approved/models/purchase_request.py
odoo_addons/purchase_request_to_rfq_order_approved/static/description/icon.png
odoo_addons/purchase_request_to_rfq_order_approved/tests/__init__.py
odoo_addons/purchase_request_to_rfq_order_approved/tests/test_purchase_request_to_rfq_order_approved.py
odoo_addons/purchase_request_to_rfq_order_approved/views/purchase_request_view.xml
