Metadata-Version: 2.1
Name: odoo9-addon-purchase-request-to-rfq-order-approved
Version: 9.0.1.0.0.99.dev5
Summary: Purchase Request to RFQ Order Approved
Home-page: http://www.eficent.com/
Author: Eficent, Odoo Community Association (OCA)
Author-email: support@odoo-community.org
License: LGPL-3
Platform: UNKNOWN
Classifier: Programming Language :: Python
Classifier: Framework :: Odoo
Classifier: License :: OSI Approved :: GNU Lesser General Public License v3 (LGPLv3)
Requires-Python: ~=2.7
Requires-Dist: odoo9-addon-purchase-order-approved
Requires-Dist: odoo9-addon-purchase-request-to-rfq
Requires-Dist: odoo (<9.1a,>=9.0a)
